rever/__init__.py
rever/__version__.py
rever-0.3.3.dist-info/LICENSE
rever-0.3.3.dist-info/METADATA
rever-0.3.3.dist-info/WHEEL
rever-0.3.3.dist-info/top_level.txt
rever-0.3.3.dist-info/RECORD
