Metadata-Version: 2.1
Name: rever
Version: 0.3.3
Summary: Rever, a retrying decorator
Home-page: http://github.com/liamcryan/rever
Author: Liam Cryan
Author-email: cryan.liam@gmail.com
License: MIT
Keywords: retry decorator rever
Platform: UNKNOWN
Classifier: Intended Audience :: Developers
Classifier: Programming Language :: Python :: 3
